nendo_plugin_caption_lpmusiccaps/__init__.py
nendo_plugin_caption_lpmusiccaps/config.py
nendo_plugin_caption_lpmusiccaps/plugin.py
nendo_plugin_caption_lpmusiccaps-0.1.2.dist-info/LICENSE
nendo_plugin_caption_lpmusiccaps-0.1.2.dist-info/METADATA
nendo_plugin_caption_lpmusiccaps-0.1.2.dist-info/WHEEL
nendo_plugin_caption_lpmusiccaps-0.1.2.dist-info/RECORD
