Metadata-Version: 2.1
Name: nendo-plugin-caption-lpmusiccaps
Version: 0.1.2
Summary: An audio captioning plugin based on LP-MusicCaps.
Home-page: https://okio.ai
License: MIT
Keywords: AI,generative,music,okio,nendo,music production,music generation,music information retrieval,audio captioning,MIR,music analysis,song analysis
Author: Aaron Abebe
Author-email: aaron@okio.ai
Requires-Python: >=3.8,<3.11
Classifier: Development Status :: 5 - Production/Stable
Classifier: Intended Audience :: Developers
Classifier: License :: OSI Approved :: MIT License
Classifier: Operating System :: OS Independent
Classifier: Programming Language :: Python :: 3
Classifier: Programming Language :: Python :: 3.8
Classifier: Programming Language :: Python :: 3.9
Classifier: Programming Language :: Python :: 3.10
Classifier: Topic :: Multimedia :: Sound/Audio
Requires-Dist: nendo (>=0.2.3,<0.3.0)
Requires-Dist: pydantic (>=2.4.2,<3.0.0)
Project-URL: Repository, https://github.com/okio-ai/nendo_plugin_caption_lpmusiccaps
